shyft/__init__.pyi
shyft/boost_filesystem-vc143-mt-x64-1_86.dll
shyft/boost_serialization-vc143-mt-x64-1_86.dll
shyft/boost_thread-vc143-mt-x64-1_86.dll
shyft/energy_market.cp311-win_amd64.pyd
shyft/hydrology.cp311-win_amd64.pyd
shyft/libcrypto-3-x64.dll
shyft/libgcc_s_seh-1.dll
shyft/libgfortran-5.dll
shyft/liblapack.dll
shyft/libquadmath-0.dll
shyft/libssl-3-x64.dll
shyft/libwinpthread-1.dll
shyft/openblas.dll
shyft/snappy.dll
shyft/time_series.cp311-win_amd64.pyd
shyft/time_series.pyi
shyft/zlib1.dll
shyft/dashboard/__init__.py
shyft/dashboard/__main__.py
shyft/dashboard/apps/__init__.py
shyft/dashboard/apps/start_bokeh_apps.py
shyft/dashboard/apps/dtss_viewer/__init__.py
shyft/dashboard/apps/dtss_viewer/dtsc_helper_functions.py
shyft/dashboard/apps/dtss_viewer/dtss_viewer_app.py
shyft/dashboard/apps/dtss_viewer/widgets.py
shyft/dashboard/apps/water_route_app/__init__.py
shyft/dashboard/apps/water_route_app/example_hps.py
shyft/dashboard/apps/water_route_app/simplified_water_route.py
shyft/dashboard/apps/water_route_app/water_route_app.py
shyft/dashboard/base/__init__.py
shyft/dashboard/base/app.py
shyft/dashboard/base/constants.py
shyft/dashboard/base/gate_model.py
shyft/dashboard/base/gate_presenter.py
shyft/dashboard/base/hashable.py
shyft/dashboard/base/ports.py
shyft/dashboard/base/selector_model.py
shyft/dashboard/base/selector_presenter.py
shyft/dashboard/base/selector_views.py
shyft/dashboard/entry_points/__init__.py
shyft/dashboard/entry_points/entry_points.py
shyft/dashboard/entry_points/start_bokeh_examples.py
shyft/dashboard/entry_points/visualize_apps.py
shyft/dashboard/examples/__init__.py
shyft/dashboard/examples/app.py
shyft/dashboard/examples/basic_bokeh_app.py
shyft/dashboard/examples/date_selector.py
shyft/dashboard/examples/figure_legend.py
shyft/dashboard/examples/gates.py
shyft/dashboard/examples/hover_tool.py
shyft/dashboard/examples/label_selector.py
shyft/dashboard/examples/message_viewer.py
shyft/dashboard/examples/multi_select_tabs.py
shyft-26.0.0.post1.dist-info/METADATA
shyft-26.0.0.post1.dist-info/WHEEL
shyft-26.0.0.post1.dist-info/entry_points.txt
shyft-26.0.0.post1.dist-info/top_level.txt
shyft-26.0.0.post1.dist-info/RECORD
