Metadata-Version: 2.1
Name: shyft
Version: 26.0.0.post1
Summary: ('Open Shyft, - An framework providing python enabled tools and services for the energy-market, hydrological forecasting and advanced time-series',)
Home-page: https://gitlab.com/shyft-os/shyft
Author: shyft
Author-email: sigbjorn.helset@gmail.com
License: LGPL v3
Platform: win-amd64
Requires: numpy
Requires-Dist: numpy
Provides-Extra: shyft.dashboard.time_series
Requires-Dist: bokeh; extra == "shyft-dashboard-time-series"
Requires-Dist: pint; extra == "shyft-dashboard-time-series"
Requires-Dist: pydot; extra == "shyft-dashboard-time-series"
Provides-Extra: shyft.hydrology.notebooks
Requires-Dist: jupyter; extra == "shyft-hydrology-notebooks"
Provides-Extra: shyft.hydrology.repositories
Requires-Dist: netcdf4; extra == "shyft-hydrology-repositories"
Requires-Dist: shapely; extra == "shyft-hydrology-repositories"
Requires-Dist: pyyaml; extra == "shyft-hydrology-repositories"
Requires-Dist: pyproj; extra == "shyft-hydrology-repositories"
Provides-Extra: shyft.hydrology.viz
Requires-Dist: matplotlib; extra == "shyft-hydrology-viz"
